MANIFEST.in
README.rst
install-sqc.sh
setup.py
.ccls-cache/@@home@daniel@informatik@pymodules@pyqcs/@home@daniel@.envs@pyqcs@lib@python3.7@site-packages@numpy@core@include@numpy@__multiarray_api.h
.ccls-cache/@@home@daniel@informatik@pymodules@pyqcs/@home@daniel@.envs@pyqcs@lib@python3.7@site-packages@numpy@core@include@numpy@__ufunc_api.h
.ccls-cache/@@home@daniel@informatik@pymodules@pyqcs/@home@daniel@.envs@pyqcs@lib@python3.7@site-packages@numpy@core@include@numpy@_neighborhood_iterator_imp.h
.ccls-cache/@@home@daniel@informatik@pymodules@pyqcs/@home@daniel@.envs@pyqcs@lib@python3.7@site-packages@numpy@core@include@numpy@_numpyconfig.h
.ccls-cache/@@home@daniel@informatik@pymodules@pyqcs/@home@daniel@.envs@pyqcs@lib@python3.7@site-packages@numpy@core@include@numpy@arrayobject.h
.ccls-cache/@@home@daniel@informatik@pymodules@pyqcs/@home@daniel@.envs@pyqcs@lib@python3.7@site-packages@numpy@core@include@numpy@ndarrayobject.h
.ccls-cache/@@home@daniel@informatik@pymodules@pyqcs/@home@daniel@.envs@pyqcs@lib@python3.7@site-packages@numpy@core@include@numpy@ndarraytypes.h
.ccls-cache/@@home@daniel@informatik@pymodules@pyqcs/@home@daniel@.envs@pyqcs@lib@python3.7@site-packages@numpy@core@include@numpy@npy_1_7_deprecated_api.h
.ccls-cache/@@home@daniel@informatik@pymodules@pyqcs/@home@daniel@.envs@pyqcs@lib@python3.7@site-packages@numpy@core@include@numpy@npy_common.h
.ccls-cache/@@home@daniel@informatik@pymodules@pyqcs/@home@daniel@.envs@pyqcs@lib@python3.7@site-packages@numpy@core@include@numpy@npy_cpu.h
.ccls-cache/@@home@daniel@informatik@pymodules@pyqcs/@home@daniel@.envs@pyqcs@lib@python3.7@site-packages@numpy@core@include@numpy@npy_endian.h
.ccls-cache/@@home@daniel@informatik@pymodules@pyqcs/@home@daniel@.envs@pyqcs@lib@python3.7@site-packages@numpy@core@include@numpy@npy_interrupt.h
.ccls-cache/@@home@daniel@informatik@pymodules@pyqcs/@home@daniel@.envs@pyqcs@lib@python3.7@site-packages@numpy@core@include@numpy@npy_math.h
.tox/py37/lib/python3.7/site-packages/PyYAML-5.4.1.dist-info/top_level.txt
.tox/py37/lib/python3.7/site-packages/aiohttp-3.7.4.dist-info/LICENSE.txt
.tox/py37/lib/python3.7/site-packages/aiohttp-3.7.4.dist-info/top_level.txt
.tox/py37/lib/python3.7/site-packages/aiohttp_cors-0.7.0.dist-info/DESCRIPTION.rst
.tox/py37/lib/python3.7/site-packages/aiohttp_cors-0.7.0.dist-info/top_level.txt
.tox/py37/lib/python3.7/site-packages/aioredis-1.3.1.dist-info/top_level.txt
.tox/py37/lib/python3.7/site-packages/async_timeout-3.0.1.dist-info/top_level.txt
.tox/py37/lib/python3.7/site-packages/attrs-20.3.0.dist-info/AUTHORS.rst
.tox/py37/lib/python3.7/site-packages/attrs-20.3.0.dist-info/top_level.txt
.tox/py37/lib/python3.7/site-packages/beautifulsoup4-4.9.3.dist-info/COPYING.txt
.tox/py37/lib/python3.7/site-packages/beautifulsoup4-4.9.3.dist-info/top_level.txt
.tox/py37/lib/python3.7/site-packages/blessings-1.7.dist-info/top_level.txt
.tox/py37/lib/python3.7/site-packages/cachetools-4.2.1.dist-info/top_level.txt
.tox/py37/lib/python3.7/site-packages/certifi-2020.12.5.dist-info/top_level.txt
.tox/py37/lib/python3.7/site-packages/chardet-3.0.4.dist-info/DESCRIPTION.rst
.tox/py37/lib/python3.7/site-packages/chardet-3.0.4.dist-info/entry_points.txt
.tox/py37/lib/python3.7/site-packages/chardet-3.0.4.dist-info/top_level.txt
.tox/py37/lib/python3.7/site-packages/click-7.1.2.dist-info/LICENSE.rst
.tox/py37/lib/python3.7/site-packages/click-7.1.2.dist-info/top_level.txt
.tox/py37/lib/python3.7/site-packages/colorama-0.4.4.dist-info/LICENSE.txt
.tox/py37/lib/python3.7/site-packages/colorama-0.4.4.dist-info/top_level.txt
.tox/py37/lib/python3.7/site-packages/colorful-0.5.4.dist-info/top_level.txt
.tox/py37/lib/python3.7/site-packages/filelock-3.0.12.dist-info/top_level.txt
.tox/py37/lib/python3.7/site-packages/google-3.0.0.dist-info/DESCRIPTION.rst
.tox/py37/lib/python3.7/site-packages/google-3.0.0.dist-info/top_level.txt
.tox/py37/lib/python3.7/site-packages/google_api_core-1.26.0.dist-info/namespace_packages.txt
.tox/py37/lib/python3.7/site-packages/google_api_core-1.26.0.dist-info/top_level.txt
.tox/py37/lib/python3.7/site-packages/google_auth-1.27.0.dist-info/namespace_packages.txt
.tox/py37/lib/python3.7/site-packages/google_auth-1.27.0.dist-info/top_level.txt
.tox/py37/lib/python3.7/site-packages/googleapis_common_protos-1.53.0.dist-info/namespace_packages.txt
.tox/py37/lib/python3.7/site-packages/googleapis_common_protos-1.53.0.dist-info/top_level.txt
.tox/py37/lib/python3.7/site-packages/gpustat-0.6.0.dist-info/entry_points.txt
.tox/py37/lib/python3.7/site-packages/gpustat-0.6.0.dist-info/top_level.txt
.tox/py37/lib/python3.7/site-packages/grpcio-1.36.0.dist-info/top_level.txt
.tox/py37/lib/python3.7/site-packages/hiredis-1.1.0.dist-info/top_level.txt
.tox/py37/lib/python3.7/site-packages/idna-2.10.dist-info/LICENSE.rst
.tox/py37/lib/python3.7/site-packages/idna-2.10.dist-info/top_level.txt
.tox/py37/lib/python3.7/site-packages/importlib_metadata-3.7.0.dist-info/top_level.txt
.tox/py37/lib/python3.7/site-packages/iniconfig-1.1.1.dist-info/top_level.txt
.tox/py37/lib/python3.7/site-packages/jsonschema-3.2.0.dist-info/entry_points.txt
.tox/py37/lib/python3.7/site-packages/jsonschema-3.2.0.dist-info/top_level.txt
.tox/py37/lib/python3.7/site-packages/msgpack-1.0.2.dist-info/top_level.txt
.tox/py37/lib/python3.7/site-packages/multidict-5.1.0.dist-info/top_level.txt
.tox/py37/lib/python3.7/site-packages/numpy-1.20.1.dist-info/LICENSE.txt
.tox/py37/lib/python3.7/site-packages/numpy-1.20.1.dist-info/LICENSES_bundled.txt
.tox/py37/lib/python3.7/site-packages/numpy-1.20.1.dist-info/entry_points.txt
.tox/py37/lib/python3.7/site-packages/numpy-1.20.1.dist-info/top_level.txt
.tox/py37/lib/python3.7/site-packages/nvidia_ml_py3-7.352.0.dist-info/top_level.txt
.tox/py37/lib/python3.7/site-packages/opencensus-0.7.12.dist-info/namespace_packages.txt
.tox/py37/lib/python3.7/site-packages/opencensus-0.7.12.dist-info/top_level.txt
