Metadata-Version: 1.2
Name: pyqcs
Version: 2.8.0
Summary: A quantum computing simulator.
Home-page: https://github.com/daknuett/pyqcs
Author: Daniel Knüttel
Author-email: daniel.knuettel@daknuett.eu
License: GNU General Public License v3 (GPLv3)
Project-URL: Source Code, https://github.com/daknuett/pyqcs
Platform: UNKNOWN
Classifier: License :: OSI Approved :: GNU General Public License v3 (GPLv3)
Requires-Python: >3.5
